{"version":"0.0.0","commands":{"build":{"id":"build","description":"describe the command here","pluginName":"@gjsify/cli","pluginType":"core","aliases":[],"examples":["$ gjsify build ./src/hello.ts"],"flags":{"help":{"name":"help","type":"boolean","char":"h","description":"show CLI help","allowNo":false},"outputFilename":{"name":"outputFilename","type":"option","char":"o","description":"File name of the output bundle","required":false,"default":"index.js"},"outputPath":{"name":"outputPath","type":"option","char":"p","description":"Output destination path","required":false,"default":"dist"},"beautify":{"name":"beautify","type":"boolean","char":"b","description":"Beautify build output","required":false,"allowNo":false},"minimize":{"name":"minimize","type":"boolean","char":"m","description":"Minimize build output","required":false,"allowNo":false}},"args":[{"name":"file"}]}}}